marhta-0.1.3.dist-info/METADATA
marhta-0.1.3.dist-info/WHEEL
marhta-0.1.3.dist-info/licenses/LICENSE
marhta/__init__.py
marhta/__init__.pyi
marhta/py.typed
marhta/marhta.cpython-311-x86_64-linux-gnu.so
marhta-0.1.3.dist-info/RECORD
