Metadata-Version: 2.4
Name: marhta
Version: 0.1.3
Classifier: Development Status :: 4 - Beta
Classifier: Programming Language :: Python :: 3
Classifier: Programming Language :: Python :: 3.8
Classifier: Programming Language :: Python :: 3.9
Classifier: Programming Language :: Python :: 3.10
Classifier: Programming Language :: Python :: 3.11
Classifier: Programming Language :: Python :: 3.12
Classifier: Programming Language :: Rust
Classifier: Topic :: Text Processing :: General
License-File: LICENSE
Summary: Fast string similarity algorithms in Rust
Keywords: string,similarity,levenshtein,jaro-winkler,fuzzy
Requires-Python: >=3.8
Project-URL: Repository, https://github.com/pjwerneck/marhta
